{
  "product": [
    {
      "id": 1,
      "name": "Dickie",
      "price": 871,
      "image": "http://dummyimage.com/275x291.png/cc0000/ffffff",
      "description": "Repair Brain, Percutaneous Endoscopic Approach"
    },
    {
      "id": 2,
      "name": "Zelda",
      "price": 442,
      "image": "http://dummyimage.com/212x281.png/ff4444/ffffff",
      "description": "Reposition L Metacarpophal Jt with Ext Fix, Perc Approach"
    },
    {
      "id": 3,
      "name": "Rooney",
      "price": 731,
      "image": "http://dummyimage.com/253x290.png/cc0000/ffffff",
      "description": "Removal of Ext Fix from L Femur Shaft, Extern Approach"
    },
    {
      "id": 4,
      "name": "Marcellus",
      "price": 151,
      "image": "http://dummyimage.com/272x285.png/cc0000/ffffff",
      "description": "Replace of L Low Leg Skin with Synth Sub, Extern Approach"
    },
    {
      "id": 5,
      "name": "Taffy",
      "price": 160,
      "image": "http://dummyimage.com/275x285.png/ff4444/ffffff",
      "description": "Reattachment of Right Spermatic Cord, Perc Endo Approach"
    },
    {
      "id": 6,
      "name": "Brooke",
      "price": 729,
      "image": "http://dummyimage.com/240x270.png/ff4444/ffffff",
      "description": "Insertion of Intralum Dev into R Renal Vein, Perc Approach"
    },
    {
      "id": 7,
      "name": "Ruggiero",
      "price": 576,
      "image": "http://dummyimage.com/289x294.png/5fa2dd/ffffff",
      "description": "Release Left Ventricle, Percutaneous Approach"
    },
    {
      "id": 8,
      "name": "Valenka",
      "price": 837,
      "image": "http://dummyimage.com/294x272.png/ff4444/ffffff",
      "description": "Occlusion of Right Anterior Tibial Artery, Open Approach"
    },
    {
      "id": 9,
      "name": "Ludovika",
      "price": 232,
      "image": "http://dummyimage.com/259x283.png/cc0000/ffffff",
      "description": "Repair Inferior Mesenteric Vein, Percutaneous Approach"
    },
    {
      "id": 10,
      "name": "Rina",
      "price": 253,
      "image": "http://dummyimage.com/245x292.png/5fa2dd/ffffff",
      "description": "Insertion of Ext Fix into L Ulna, Perc Endo Approach"
    },
    {
      "id": 10,
      "name": "Rina",
      "price": 253,
      "image": "http://dummyimage.com/245x292.png/5fa2dd/ffffff",
      "description": "Insertion of Ext Fix into L Ulna, Perc Endo Approach"
    },
    {
      "id": 10,
      "name": "Rina",
      "price": 253,
      "image": "http://dummyimage.com/245x292.png/5fa2dd/ffffff",
      "description": "Insertion of Ext Fix into L Ulna, Perc Endo Approach"
    }
  ]
}